CHANGES.txt
README.txt
bootstrap.py
buildout.cfg
setup.py
src/z3c/__init__.py
src/z3c.viewlet.egg-info/PKG-INFO
src/z3c.viewlet.egg-info/SOURCES.txt
src/z3c.viewlet.egg-info/dependency_links.txt
src/z3c.viewlet.egg-info/namespace_packages.txt
src/z3c.viewlet.egg-info/not-zip-safe
src/z3c.viewlet.egg-info/requires.txt
src/z3c.viewlet.egg-info/top_level.txt
src/z3c/viewlet/README.txt
src/z3c/viewlet/__init__.py
src/z3c/viewlet/manager.py
src/z3c/viewlet/tests.py