Metadata-Version: 1.0
Name: z3c.viewlet
Version: 1.1.0
Summary: DEPRCATED: Collection of Viewlet Extensions
Home-page: http://pypi.python.org/pypi/z3c.viewlet
Author: Zope Corporation and Contributors
Author-email: zope-dev@zope.org
License: ZPL 2.1
Keywords: zope3 viewlet extension weight ordered
Platform: UNKNOWN
Classifier: Development Status :: 7 - Inactive
Classifier: Environment :: Web Environment
Classifier: Intended Audience :: Developers
Classifier: License :: OSI Approved :: Zope Public License
Classifier: Programming Language :: Python
Classifier: Natural Language :: English
Classifier: Operating System :: OS Independent
Classifier: Topic :: Internet :: WWW/HTTP
Classifier: Framework :: Zope3
